[{"name": "mid", "value": "YdK_7wALAAH9DzKXDPA_BvIO5xur", "domain": ".instagram.com", "path": "/", "expires": 1704273648.514075, "size": 31, "httpOnly": false, "secure": true, "session": false}, {"name": "ig_did", "value": "10262179-1172-42D1-A8DB-9C1D81610438", "domain": ".instagram.com", "path": "/", "expires": 1704273648.514096, "size": 42, "httpOnly": true, "secure": true, "session": false}, {"name": "ig_nrcb", "value": "1", "domain": ".instagram.com", "path": "/", "expires": 1672737648.514119, "size": 8, "httpOnly": false, "secure": true, "session": false}, {"name": "csrftoken", "value": "llMinlZJ9liSK1n3NPuHDYcaAoSCd6ER", "domain": ".instagram.com", "path": "/", "expires": 1672651257.112948, "size": 41, "httpOnly": false, "secure": true, "session": false}, {"name": "sessionid", "value": "4526877383%3AKTX65GR3wkNC4U%3A19", "domain": ".instagram.com", "path": "/", "expires": 1672737652.684301, "size": 41, "httpOnly": true, "secure": true, "session": false}, {"name": "ds_user_id", "value": "4526877383", "domain": ".instagram.com", "path": "/", "expires": 1648977657.113017, "size": 20, "httpOnly": false, "secure": true, "session": false}, {"name": "shbts", "value": "\"1641201652\\0544526877383\\0541672737652:01f728563893ac6e95b43e457c7d13cc636eecab4e5e55810397dea292b0368b617770f4\"", "domain": ".instagram.com", "path": "/", "expires": 1641806453.04155, "size": 118, "httpOnly": true, "secure": true, "session": false}, {"name": "shbid", "value": "\"18885\\0544526877383\\0541672737652:01f785bd4be5751483944034387434eddfab3f1e74a61211b064673b6d431d66214bcbc8\"", "domain": ".instagram.com", "path": "/", "expires": 1641806453.041527, "size": 113, "httpOnly": true, "secure": true, "session": false}, {"name": "rur", "value": "\"ATN\\0544526877383\\0541672737656:01f76d0e57a0512e2f6dc4fc3c4a1eedab71e17ef04bfb7bef862c1f4c7184f8d20e20ab\"", "domain": ".instagram.com", "path": "/", "expires": -1, "size": 109, "httpOnly": true, "secure": true, "session": true}]